{
  "101": "GB",
  "102": "AT",
  "103": "CZ",
  "104": "DE",
  "105": "FI",
  "106": "US",
  "107": "AT",
  "108": "IT",
  "109": "BV",
  "110": "DE",
  "111": "PE",
  "112": "US",
  "113": "GB",
  "114": "CZ",
  "115": "DE",
  "116": "PH",
  "117": "US",
  "118": "FR",
  "119": "AT",
  "120": "GB",
  "121": "SA",
  "122": "FR",
  "123": "US",
  "124": "GB",
  "125": "US",
  "126": "AE",
  "127": "DE",
  "128": "FR",
  "129": "GB",
  "130": "CZ",
  "131": "DE",
  "132": "CZ",
  "133": "CZ",
  "134": "CZ",
  "135": "DE",
  "136": "CZ",
  "137": "US",
  "138": "GB",
  "139": "FR",
  "140": "CZ",
  "141": "IT",
  "142": "CZ",
  "143": "CZ",
  "144": "US",
  "145": "CZ",
  "146": "CZ",
  "147": "CH",
  "148": "CZ",
  "149": "CZ",
  "150": "GB",
  "151": "CZ",
  "152": "AT",
  "153": "CZ",
  "154": "CZ",
  "155": "DE",
  "156": "CZ",
  "157": "CZ",
  "158": "FR",
  "159": "CZ",
  "160": "IN",
  "161": "CZ",
  "162": "CZ",
  "163": "IT",
  "164": "CZ",
  "165": "CZ",
  "166": "CZ",
  "167": "DE",
  "168": "AT",
  "169": "US",
  "170": "CZ",
  "171": "US",
  "172": "CZ",
  "173": "CZ",
  "174": "US",
  "175": "CH",
  "176": "CZ",
  "177": "DE",
  "178": "CZ",
  "179": "CZ",
  "180": "JP",
  "181": "CZ",
  "182": "CZ",
  "183": "CZ",
  "184": "CZ",
  "185": "US",
  "186": "DE",
  "187": "US",
  "188": "CZ",
  "189": "DE",
  "190": "CZ",
  "191": "US",
  "192": "GB",
  "193": "CZ",
  "194": "DE",
  "195": "CZ",
  "196": "US",
  "197": "CZ",
  "198": "AT",
  "199": "GB",
  "200": "CZ",
  "201": "FR",
  "202": "US",
  "203": "GB",
  "204": "US",
  "205": "CZ",
  "206": "DE",
  "207": "FR",
  "208": "GB",
  "209": "CZ",
  "210": "DE",
  "211": "CZ",
  "212": "CZ",
  "213": "CZ",
  "214": "DE",
  "215": "CZ",
  "216": "US",
  "217": "GB",
  "218": "FR",
  "219": "CZ",
  "220": "IT",
  "221": "CZ",
  "222": "CZ",
  "223": "US",
  "224": "CZ",
  "225": "CZ",
  "226": "CH",
  "227": "CZ",
  "228": "CZ",
  "229": "GB",
  "230": "CZ",
  "231": "AT",
  "232": "CZ",
  "233": "CZ",
  "234": "DE",
  "235": "CZ",
  "236": "CZ",
  "237": "FR",
  "238": "CZ",
  "239": "IN",
  "240": "CZ",
  "241": "CZ",
  "242": "IT",
  "243": "CZ",
  "244": "CZ",
  "245": "CZ",
  "246": "DE",
  "247": "AT",
  "248": "US",
  "249": "CZ",
  "250": "US",
  "251": "CZ",
  "252": "CZ",
  "253": "US",
  "254": "CH",
  "255": "CZ",
  "256": "DE",
  "257": "CZ",
  "258": "CZ",
  "259": "JP",
  "260": "CZ",
  "261": "CZ",
  "262": "CZ",
  "263": "CZ",
  "264": "US",
  "265": "DE",
  "266": "US",
  "267": "CZ",
  "268": "DE",
  "269": "CZ",
  "270": "US",
  "271": "GB",
  "272": "CZ",
  "273": "DE",
  "274": "CZ",
  "275": "US",
  "276": "CZ",
  "277": "AT",
  "278": "GB",
  "279": "CZ",
  "280": "FR"
}